di_toolkit-0.3.0.dist-info/licenses/LICENSE
ditk/__init__.py
ditk/config/__init__.py
ditk/config/meta.py
ditk/distributed/__init__.py
ditk/distributed/env.py
ditk/doc/__init__.py
ditk/doc/annotated/__init__.py
ditk/doc/annotated/__main__.py
ditk/doc/annotated/generate.py
ditk/doc/annotated/ppo.py
ditk/doc/annotated/pylit.css
ditk/doc/annotated/solarized.css
ditk/logging/__init__.py
ditk/logging/base.py
ditk/logging/explicit.py
ditk/logging/file.py
ditk/logging/func.py
ditk/logging/inherit.py
ditk/logging/log.py
ditk/logging/rich.py
ditk/logging/stream.py
ditk/logging/terminal.py
ditk/tensorboard/__init__.py
ditk/tensorboard/log.py
ditk/tensorboard/plots/__init__.py
ditk/tensorboard/plots/range.py
di_toolkit-0.3.0.dist-info/METADATA
di_toolkit-0.3.0.dist-info/WHEEL
di_toolkit-0.3.0.dist-info/top_level.txt
di_toolkit-0.3.0.dist-info/RECORD
