Metadata-Version: 2.4
Name: DI-toolkit
Version: 0.3.0
Summary: A simple tool for opendilab.
Home-page: https://github.com/opendilab/DI-toolkit
Author: HansBug
Author-email: hansbug@buaa.edu.cn
License: Apache License, Version 2.0
Keywords: opendilab,toolkit,logging,documentation,tensorboard,machine learning,deep learning,reinforcement learning
Classifier: Development Status :: 5 - Production/Stable
Classifier: Intended Audience :: Developers
Classifier: Intended Audience :: Science/Research
Classifier: Intended Audience :: Information Technology
Classifier: License :: OSI Approved :: Apache Software License
Classifier: Programming Language :: Python
Classifier: Programming Language :: Python :: 3
Classifier: Programming Language :: Python :: 3.8
Classifier: Programming Language :: Python :: 3.9
Classifier: Programming Language :: Python :: 3.10
Classifier: Programming Language :: Python :: 3.11
Classifier: Programming Language :: Python :: 3.12
Classifier: Programming Language :: Python :: 3.13
Classifier: Programming Language :: Python :: Implementation :: PyPy
Classifier: Operating System :: OS Independent
Classifier: Operating System :: POSIX
Classifier: Operating System :: Microsoft :: Windows
Classifier: Operating System :: MacOS
Classifier: Topic :: Software Development :: Libraries :: Python Modules
Classifier: Topic :: Software Development :: Documentation
Classifier: Topic :: System :: Logging
Classifier: Topic :: Scientific/Engineering :: Artificial Intelligence
Classifier: Topic :: Scientific/Engineering :: Information Analysis
Classifier: Topic :: Scientific/Engineering :: Visualization
Classifier: Topic :: Utilities
Classifier: Environment :: Console
Classifier: Environment :: Web Environment
Classifier: Natural Language :: English
Classifier: Natural Language :: Chinese (Simplified)
Classifier: Framework :: Matplotlib
Classifier: Topic :: Software Development :: Libraries :: Application Frameworks
Classifier: Topic :: Text Processing :: Markup :: HTML
Requires-Python: >=3.8
License-File: LICENSE
Requires-Dist: hbutils>=0.9.1
Requires-Dist: rich>=12.2.0
Requires-Dist: yattag>=1.14.0
Requires-Dist: click>=7.0.0
Requires-Dist: pandas
Requires-Dist: tensorboard
Requires-Dist: tqdm
Requires-Dist: scipy
Requires-Dist: scikit-learn
Requires-Dist: seaborn
Requires-Dist: matplotlib
Provides-Extra: test
Requires-Dist: coverage>=5; extra == "test"
Requires-Dist: mock>=4.0.3; extra == "test"
Requires-Dist: flake8~=3.5; extra == "test"
Requires-Dist: testfixtures>=6.18.5; extra == "test"
Requires-Dist: pytest~=6.2.5; extra == "test"
Requires-Dist: pytest-cov~=3.0.0; extra == "test"
Requires-Dist: pytest-mock~=3.6.1; extra == "test"
Requires-Dist: pytest-xdist>=1.34.0; extra == "test"
Requires-Dist: pytest-rerunfailures~=10.2; extra == "test"
Requires-Dist: pytest-timeout~=2.0.2; extra == "test"
Requires-Dist: pytest-benchmark~=3.4.0; extra == "test"
Requires-Dist: easydict<2,>=1.7; extra == "test"
Requires-Dist: testtools>=2; extra == "test"
Requires-Dist: where>=1.0.2; extra == "test"
Requires-Dist: pytest-image-diff>=0.0.11; extra == "test"
Requires-Dist: natsort; extra == "test"
Provides-Extra: style
Requires-Dist: yapf==0.29.0; extra == "style"
Requires-Dist: flake8<5,>=3; extra == "style"
Provides-Extra: doc
Requires-Dist: Jinja2>=3.0.0; extra == "doc"
Requires-Dist: sphinx<8,>=3.2.0; extra == "doc"
Requires-Dist: sphinx_rtd_theme>=0.4.3; extra == "doc"
Requires-Dist: enum_tools>=0.9.0; extra == "doc"
Requires-Dist: sphinx-toolbox; extra == "doc"
Requires-Dist: plantumlcli>=0.0.2; extra == "doc"
Requires-Dist: packaging; extra == "doc"
Requires-Dist: sphinx-multiversion>=0.2.4; extra == "doc"
Requires-Dist: where>=1.0.2; extra == "doc"
Requires-Dist: easydict<2,>=1.7; extra == "doc"
Dynamic: author
Dynamic: author-email
Dynamic: classifier
Dynamic: description
Dynamic: description-content-type
Dynamic: home-page
Dynamic: keywords
Dynamic: license
Dynamic: license-file
Dynamic: provides-extra
Dynamic: requires-dist
Dynamic: requires-python
Dynamic: summary
